mqtt_rest/__init__.py
mqtt_rest/configs.py
mqtt_rest/db.py
mqtt_rest/device.py
mqtt_rest/mqtt.py
mqtt_rest/plugins/__init__.py
mqtt_rest/plugins/report_manager.py
mqtt_rest/plugins/routes.py
mqtt_rest/plugins/simple_plugin.py
mqtt_rest/plugins/simple_plugin_templates/install.sh
mqtt_rest/plugins/simple_plugin_templates/multi_job.sh
mqtt_rest/plugins/simple_plugin_templates/report.txt
mqtt_rest/plugins/simple_plugin_templates/single_job.sh
mqtt_rest/plugins/simple_plugins/__init__.py
mqtt_rest/plugins/simple_plugins/sensors.py
mqtt_rest/plugins/simple_plugins/smartwrt.py
mqtt_rest/plugins/simple_template_engine.py
mqtt_rest/run.py
mqtt_rest/server.py
mqtt_rest/utils.py
mqtt_rest-0.8.1.dist-info/LICENSE
mqtt_rest-0.8.1.dist-info/METADATA
mqtt_rest-0.8.1.dist-info/WHEEL
mqtt_rest-0.8.1.dist-info/entry_points.txt
mqtt_rest-0.8.1.dist-info/RECORD
