Metadata-Version: 2.1
Name: mqtt-rest
Version: 0.8.1
Summary: A REST API for MQTT Client Management
Home-page: https://github.com/rahulsrma26/mqtt-rest
License: MIT
Keywords: MQTT,REST,API
Author: Rahul Sharma
Author-email: rahulsrma26@gmail.com
Maintainer: Rahul Sharma
Maintainer-email: rahulsrma26@gmail.com
Requires-Python: >=3.11,<4.0
Classifier: Framework :: FastAPI
Classifier: License :: OSI Approved :: MIT License
Classifier: Programming Language :: Python :: 3
Classifier: Programming Language :: Python :: 3.11
Classifier: Programming Language :: Python :: 3.12
Classifier: Programming Language :: Python :: 3.13
Classifier: Topic :: Home Automation
Requires-Dist: fastapi (>=0.115.0,<0.116.0)
Requires-Dist: jinja2 (>=3.1.4,<4.0.0)
Requires-Dist: paho-mqtt (>=2.1.0,<3.0.0)
Requires-Dist: sqlmodel (>=0.0.22,<0.0.23)
Requires-Dist: toml (>=0.10.2,<0.11.0)
Requires-Dist: uvicorn (>=0.31.0,<0.32.0)
Project-URL: Repository, https://github.com/rahulsrma26/mqtt-rest
